{"cameraMode":{"drawMode":0,"name":"Shaded","section":"Shading Mode"},"sceneLighting":false,"audioPlay":false,"sceneViewState":{"m_AlwaysRefresh":false,"showFog":true,"showSkybox":false,"showFlares":true,"showImageEffects":true,"showParticleSystems":true,"showVisualEffectGraphs":true,"m_FxEnabled":true},"in2DMode":false,"pivot":{"x":0.00990149937570095,"y":2.8258817195892336,"z":-0.5179275870323181},"rotation":{"x":0.00008709909161552787,"y":-0.9995631575584412,"z":0.030306192114949228,"w":0.00360615411773324},"size":1.6538236141204835,"orthographic":false}